{
  "_meta": { "license": "CC BY-NC 4.0", "version": 1, "authoredOn": "2026-05-05", "notes": "Bell-keeper at Furrowmouth. Knows which day is which grain by ear before they read the chalkboard." },
  "id": "furrowmouth-bell-keeper",
  "displayName": "Old Lis",
  "kind": "npc",
  "tagline": "small, tidy, faintly always smells of grain dust; rings the bell as if it owes her something.",
  "vitals": { "hp": { "max": 5, "start": 5 } },
  "stats": { "awareness": 3, "patience": 3, "will": 2 },
  "attitudeDefault": 2,
  "attitudeRange": [0, 3],
  "tags": ["human", "furrowmouth", "bell-keeper", "recurring"],
  "metadata": {
    "templateId": "furrowmouth-bell-keeper",
    "recurring": true,
    "voice": "warm, direct, fond of the elven wholesalers in a way that confuses them",
    "topicsOfInterest": ["which grain is in season", "the wholesalers' arrival times", "her son's barley"],
    "appearanceProbability": { "baseLow": 0.05, "baseHigh": 0.08, "wyrmPhaseThreshold": 500, "perPriorEncounterBonus": 0.02, "maxAppearanceProbability": 0.20 }
  }
}
